exodus/auth.py
exodus/cli.py
exodus/kv_migrator.py
exodus/namespace.py
exodus/secret.py
exodus/├─ __init__.py
vault_exodus-0.1.3.7.dist-info/LICENSE
vault_exodus-0.1.3.7.dist-info/METADATA
vault_exodus-0.1.3.7.dist-info/WHEEL
vault_exodus-0.1.3.7.dist-info/entry_points.txt
vault_exodus-0.1.3.7.dist-info/top_level.txt
vault_exodus-0.1.3.7.dist-info/RECORD
