Metadata-Version: 2.2
Name: vault-exodus
Version: 0.1.3.7
Summary: A community-driven tool for migrating HashiCorp Vault secrets between KV engines (v1/v2). Use at your own RISK
Author-email: AndyLow <memebotandres@gmail.com>
License: MIT
Project-URL: Source Code, https://github.com/andylow92/exodus
Project-URL: Tracker, https://github.com/andylow92/exodus/issues
Keywords: vault,hashicorp,migration,secrets
Classifier: Programming Language :: Python :: 3
Classifier: License :: OSI Approved :: MIT License
Classifier: Operating System :: OS Independent
Requires-Python: >=3.7
License-File: LICENSE
Requires-Dist: requests>=2.20.0
Requires-Dist: tqdm
Requires-Dist: dataclasses; python_version < "3.7"
